{
    
	"item1":
	{
		"url": "https://www.youtube.com/embed/rpYq1lSce1U",
		"num": 1,
		"author": "officialpsy",
		"title": "PSY - KOREA M/V",
		"runtime": "03:51"
	},
    
	"item2":
	{
		"url": "https://www.youtube.com/embed/gfmjMWjn-Xg",
		"num": 2,
		"author": "officialpsy",
		"title": "PSY - '어땠을까 (What Would Have Been)' 0528 SBS Fantastic Duo 2",
		"runtime": "04:10"
	},
	
	"item3":
	{
		"url": "https://www.youtube.com/embed/9bZkp7q19f0",
		"num": 3,
		"author": "officialpsy",
		"title": "PSY - GANGNAM STYLE(강남스타일) M/V",
		"runtime": "04:12"
	},
	
	"item4":
	{
		"url": "https://www.youtube.com/embed/zFbvqLPEvMs",
		"num": 4,
		"author": "THE BRWZ",
		"title": "PSY - ‘New Face’ MV REACTION !!!!!!!!!",
		"runtime": "04:59"
	},

	"item5":
	{
		"url": "https://www.youtube.com/embed/lyiUh62L0IY",
		"num": 5,
		"author": "퍼크 TV",
		"title": "[리액션 한글자막] 미국 대학생들이 싸이 뉴페이스,I luv it을 봤을 때 반응",
		"runtime": "08:53"
	}

}

